haveno_client/__init__.py
haveno_client/cli.py
haveno_client/client.py
haveno_client/grpc_pb2.py
haveno_client/grpc_pb2_grpc.py
haveno_client/pb_pb2.py
haveno_client/pb_pb2_grpc.py
haveno_client/clients/__init__.py
haveno_client/clients/account_client.py
haveno_client/clients/disputes_client.py
haveno_client/clients/offers_client.py
haveno_client/clients/payment_accounts_client.py
haveno_client/clients/trades_stub_client.py
haveno_client/proto2/grpc_pb2.py
haveno_client/proto2/grpc_pb2_grpc.py
haveno_client/proto2/pb_pb2.py
haveno_client/proto2/pb_pb2_grpc.py
haveno_client/stubs/__init__.py
haveno_client/stubs/server_info_stub.py
haveno_client-0.2.2.dist-info/licenses/LICENSE
haveno_client-0.2.2.dist-info/METADATA
haveno_client-0.2.2.dist-info/WHEEL
haveno_client-0.2.2.dist-info/entry_points.txt
haveno_client-0.2.2.dist-info/top_level.txt
haveno_client-0.2.2.dist-info/RECORD
