Metadata-Version: 2.4
Name: haveno-client
Version: 0.2.2
Summary: A client for interacting with the Haveno daemon.
Author-email: Kewbit <support@haveno.app>
License: AGPL-3.0-or-later
Project-URL: Homepage, https://haveno.app
Project-URL: Repository, https://git.haveno.app/haveno-network/python-haveno-client
Project-URL: Issues, https://git.haveno.app/haveno-network/python-haveno-client/issues
Project-URL: Documentation, https://haveno.app/documentation
Project-URL: Changelog, https://haveno.app/changelog
Project-URL: Funding, https://haveno.app/donate
Keywords: haveno,monero,p2p,exchange
Classifier: Development Status :: 3 - Alpha
Classifier: Intended Audience :: Developers
Classifier: License :: OSI Approved :: GNU Affero General Public License v3 or later (AGPLv3+)
Classifier: Programming Language :: Python
Classifier: Programming Language :: Python :: 3
Classifier: Programming Language :: Python :: 3 :: Only
Classifier: Programming Language :: Python :: 3.8
Classifier: Programming Language :: Python :: 3.9
Classifier: Programming Language :: Python :: 3.10
Classifier: Programming Language :: Python :: 3.11
Classifier: Programming Language :: Python :: 3.12
Classifier: Operating System :: OS Independent
Requires-Python: >=3.8
License-File: LICENSE
Requires-Dist: grpcio
Requires-Dist: socks
Provides-Extra: codegen
Requires-Dist: grpcio-tools; extra == "codegen"
Dynamic: license-file
